setup.py
gentle/__init__.py
gentle/rm.py
gentletool.egg-info/PKG-INFO
gentletool.egg-info/SOURCES.txt
gentletool.egg-info/dependency_links.txt
gentletool.egg-info/entry_points.txt
gentletool.egg-info/top_level.txt