Metadata-Version: 1.0
Name: gentletool
Version: 0.2
Summary: some gentle tool
Home-page: https://github.com/airhuman/gentletool
Author: liyong
Author-email: liyong19861014@gmail.com
License: UNKNOWN
Platform: UNKNOWN
